android_strings_converter/__init__.py
android_strings_converter/__main__.py
android_strings_converter/console_style.py
android_strings_converter/converter.py
android_strings_converter-0.1.3.dist-info/METADATA
android_strings_converter-0.1.3.dist-info/WHEEL
android_strings_converter-0.1.3.dist-info/LICENSE
android_strings_converter-0.1.3.dist-info/RECORD
