Metadata-Version: 2.1
Name: android-strings-converter
Version: 0.1.3
Summary: Android strings.xml file converter to any file type supported by the package.
Home-page: https://github.com/HenestrosaConH/android-strings-converter
License: MIT
Keywords: android,strings.xml,strings,converter,csv,xlsx,yaml,html,json,ods
Author: José Carlos López
Author-email: henestrosaconh@gmail.com
Requires-Python: >=3.10,<4.0
Classifier: Environment :: Console
Classifier: Intended Audience :: Developers
Classifier: License :: OSI Approved :: MIT License
Classifier: Operating System :: MacOS
Classifier: Operating System :: Microsoft :: Windows
Classifier: Operating System :: OS Independent
Classifier: Operating System :: Other OS
Classifier: Operating System :: POSIX :: Linux
Classifier: Programming Language :: Python :: 3
Classifier: Programming Language :: Python :: 3.10
Classifier: Programming Language :: Python :: 3.11
Classifier: Programming Language :: Python :: 3
Classifier: Topic :: Text Processing :: General
Classifier: Topic :: Utilities
Requires-Dist: gspread (>=5.7.2,<6.0.0)
Requires-Dist: openpyxl (>=3.1.0,<4.0.0)
Requires-Dist: protobuf (>=4.21.12,<5.0.0)
Requires-Dist: pyyaml (>=6.0,<7.0)
Project-URL: Repository, https://github.com/HenestrosaConH/android-strings-converter
